legal_pre_processing/__init__.py
legal_pre_processing/heuristics.py
legal_pre_processing/legal_pre_processing.py
legal_pre_processing/utils.py
legal_pre_processing-0.3.2.dist-info/WHEEL
legal_pre_processing-0.3.2.dist-info/METADATA
legal_pre_processing-0.3.2.dist-info/RECORD
