Metadata-Version: 2.1
Name: legal-pre-processing
Version: 0.3.2
Summary: Pre processing tools for documents with legal content.
Home-page: https://gitlab.com/israel.oliveira.softplan/legal-pre-processing.git
License: MIT
Keywords: legal,text,extract
Author: Daniel Henrique Arruda Boeing
Author-email: daniel.boeing@softplan.com.br
Requires-Python: >=3.7
Classifier: License :: OSI Approved :: MIT License
Classifier: Programming Language :: Python :: 3
Classifier: Programming Language :: Python :: 3.7
Classifier: Programming Language :: Python :: 3.8
Classifier: Programming Language :: Python :: 3.9
Requires-Dist: PyMuPDF (>=1.10)
Requires-Dist: Unidecode (>=1.0)
Requires-Dist: nltk (>=3.5)
Project-URL: Repository, https://gitlab.com/israel.oliveira.softplan/legal-pre-processing.git
